lib_detect_encoding/__init__.py
lib_detect_encoding/__init__conf__.py
lib_detect_encoding/lib_detect_encoding.py
lib_detect_encoding/lib_detect_encoding_cli.py
lib_detect_encoding/py.typed
lib_detect_encoding-1.0.1.dist-info/LICENSE
lib_detect_encoding-1.0.1.dist-info/METADATA
lib_detect_encoding-1.0.1.dist-info/WHEEL
lib_detect_encoding-1.0.1.dist-info/entry_points.txt
lib_detect_encoding-1.0.1.dist-info/top_level.txt
lib_detect_encoding-1.0.1.dist-info/RECORD
