Metadata-Version: 2.1
Name: lib-detect-encoding
Version: 1.0.1
Summary: detects encodings of raw files, or the system default encoding
Author-email: Robert Nowotny <bitranox@gmail.com>
License: MIT
Project-URL: Homepage, https://github.com/bitranox/lib_detect_encoding
Project-URL: Documentation, https://github.com/bitranox/lib_detect_encoding/blob/master/README.rst
Project-URL: Repository, https://github.com/bitranox/lib_detect_encoding.git
Project-URL: Changelog, https://github.com/bitranox/lib_detect_encoding/blob/master/CHANGES.rst
Classifier: Development Status :: 5 - Production/Stable
Classifier: Intended Audience :: Developers
Classifier: License :: OSI Approved :: MIT License
Classifier: Natural Language :: English
Classifier: Operating System :: OS Independent
Classifier: Programming Language :: Python
Classifier: Topic :: Software Development :: Libraries :: Python Modules
Requires-Python: >=3.8.0
License-File: LICENSE
Requires-Dist: chardet
Requires-Dist: cli-exit-tools
Requires-Dist: click
Requires-Dist: lib-log-utils
Requires-Dist: lib-platform
Provides-Extra: test
Requires-Dist: black ; extra == 'test'
Requires-Dist: codecov ; extra == 'test'
Requires-Dist: coloredlogs ; extra == 'test'
Requires-Dist: coverage ; extra == 'test'
Requires-Dist: flake8 ; extra == 'test'
Requires-Dist: mypy ; extra == 'test'
Requires-Dist: pytest ; extra == 'test'
Requires-Dist: pytest-cov ; extra == 'test'
Requires-Dist: pytest-runner ; extra == 'test'
Requires-Dist: readme-renderer ; extra == 'test'
